coinor/dippy/DippyDecompAlgo.cpp
coinor/dippy/DippyDecompApp.cpp
coinor/dippy/DippyModule.cpp
coinor/dippy/DippyPythonUtils.cpp
coinor/dippy/DippySolve.cpp
coinor/dippy/__init__.py
coinor/dippy/_dippy.cpython-313-aarch64-linux-gnu.so
coinor/dippy/dipapi.py
coinor/dippy/dippy.py
coinor/dippy/examples/__init__.py
coinor/dippy/examples/__main__.py
coinor/dippy/examples/gen_func.py
coinor/dippy/examples/SolverStudio/__init__.py
coinor/dippy/examples/bpp/__init__.py
coinor/dippy/examples/bpp/__main__.py
coinor/dippy/examples/bpp/bin_pack_decomp_func.py
coinor/dippy/examples/bpp/bin_pack_func.py
coinor/dippy/examples/bpp/bin_pack_instance.py
coinor/dippy/examples/bpp/bin_pack_instance2.py
coinor/dippy/examples/bpp/bpp_data.py
coinor/dippy/examples/bpp/mdbin_pack_func.py
coinor/dippy/examples/bpp/mdbin_pack_instance.py
coinor/dippy/examples/cflp/__init__.py
coinor/dippy/examples/cflp/__main__.py
coinor/dippy/examples/cflp/facility_data1.py
coinor/dippy/examples/cflp/facility_data2.py
coinor/dippy/examples/cflp/facility_location_func.py
coinor/dippy/examples/coke/__init__.py
coinor/dippy/examples/coke/__main__.py
coinor/dippy/examples/coke/coke_data.py
coinor/dippy/examples/coke/coke_func.py
coinor/dippy/examples/csp/__init__.py
coinor/dippy/examples/csp/__main__.py
coinor/dippy/examples/csp/cutting_stock_data.py
coinor/dippy/examples/csp/cutting_stock_func.py
coinor/dippy/examples/cvpmp/CVPMP.py
coinor/dippy/examples/cvpmp/Global.py
coinor/dippy/examples/cvpmp/__init__.py
coinor/dippy/examples/cvpmp/__main__.py
coinor/dippy/examples/cvpmp/draw.py
coinor/dippy/examples/cvpmp/readInstance.py
coinor/dippy/examples/gap/__init__.py
coinor/dippy/examples/gap/__main__.py
coinor/dippy/examples/gap/gap0515-2.py
coinor/dippy/examples/gap/gap_func.py
coinor/dippy/examples/milp/__init__.py
coinor/dippy/examples/milp/__main__.py
coinor/dippy/examples/milp/milp_func.py
coinor/dippy/examples/tsp/__init__.py
coinor_dippy-1.95.4.dist-info/METADATA
coinor_dippy-1.95.4.dist-info/WHEEL
coinor_dippy-1.95.4.dist-info/top_level.txt
coinor_dippy-1.95.4.dist-info/RECORD
coinor_dippy-1.95.4.dist-info/licenses/AUTHORS
coinor_dippy-1.95.4.dist-info/licenses/LICENSE
