Metadata-Version: 2.4
Name: coinor.dippy
Version: 1.95.4
Summary: DIP Python Interface
Author: Qi-Shan Lim, Stuart Mitchell
Author-email: Michael O'Sullivan <michael.osullivan@auckland.ac.nz>, Ted Ralphs <ted@lehigh.edu>
License-Expression: EPL-2.0
Project-URL: Home Page, https://github.com/coin-or/DIP
License-File: LICENSE
License-File: AUTHORS
Requires-Dist: pulp<=2.9.0,>=1.5.4
Requires-Dist: coinor.gimpy>=2.0.0
Requires-Dist: future
Dynamic: license-file
